jingjue/__init__.py
jingjue/gua_dict.py
jingjue/jingjue.py
jingjue-1.1.dist-info/METADATA
jingjue-1.1.dist-info/WHEEL
jingjue-1.1.dist-info/top_level.txt
jingjue-1.1.dist-info/RECORD
