Metadata-Version: 2.1
Name: jingjue
Version: 1.1
Summary: Jingjue is an ancient Chinese divination method similar as ichingshifa found from a bunch of bamboo slips relics collected by Peking University
Home-page: https://github.com/kentang2017/jingjue
Author: Ken Tang
Author-email: kinyeah@gmail.com
License: UNKNOWN
Platform: UNKNOWN
Classifier: Programming Language :: Python :: 3
Classifier: License :: OSI Approved :: MIT License
Classifier: Operating System :: OS Independent
